LICENSE
MANIFEST.in
README.md
foxyproxy-runner.py
setup.py
foxyproxy/.DS_Store
foxyproxy/__init__.py
foxyproxy/__main__.py
foxyproxy/beacon_thread.py
foxyproxy/client_thread.py
foxyproxy/constant.py
foxyproxy/create_csr.py
foxyproxy/foxy_proxy_rest.py
foxyproxy/foxy_proxy_tcp.py
foxyproxy/log_dispatcher.py
foxyproxy/logger.py
foxyproxy/queue_handler.py
foxyproxy/request_data.py
foxyproxy/setup.cfg
foxyproxy/test_get.py
foxyproxy/version.py
foxyproxy.egg-info/PKG-INFO
foxyproxy.egg-info/SOURCES.txt
foxyproxy.egg-info/dependency_links.txt
foxyproxy.egg-info/entry_points.txt
foxyproxy.egg-info/namespace_packages.txt
foxyproxy.egg-info/requires.txt
foxyproxy.egg-info/top_level.txt
foxyproxy/csp/__init__.py
foxyproxy/csp/base_csp.py
foxyproxy/csp/ica.py
foxyproxy/csp/pgp.py
foxyproxy/csp/postsignum.py
foxyproxy/csp/register.py
foxyproxy/csp/test_smartcard.py
foxyproxy/issuers/__init__.py
foxyproxy/issuers/comodo.py
foxyproxy/tests/__init__.py
foxyproxy/tests/test_baseCryptoService.py
foxyproxy/upstream/__init__.py
foxyproxy/upstream/base_upstream.py
foxyproxy/upstream/cloudfoxy.py
foxyproxy/upstream/globalplatform.py
foxyproxy/upstream/linuxshell.py
foxyproxy/upstream/pythoncard.py
foxyproxy/upstream/register.py