Metadata-Version: 2.1
Name: foxyproxy
Version: 2.8.8
Summary: TCP/RESTful proxy for Cloud Foxy - cloud platform for smart cards
Home-page: http://cloudfoxy.com
Author: Smart Arcs Ltd (built on an inital code by Enigma Bridge Ltd)
Author-email: support@smartarchitects.co.uk
License: UNKNOWN
Platform: UNKNOWN
Classifier: Development Status :: 3 - Alpha
Classifier: Intended Audience :: Developers
Classifier: Programming Language :: Python
Classifier: Programming Language :: Python :: 2
Classifier: Programming Language :: Python :: 2.6
Classifier: Programming Language :: Python :: 2.7
Classifier: Programming Language :: Python :: 3
Classifier: Programming Language :: Python :: 3.3
Classifier: Programming Language :: Python :: 3.4
Classifier: Programming Language :: Python :: 3.5
Classifier: Programming Language :: Python :: 3.6
Classifier: Programming Language :: Python :: 3.7
Classifier: Topic :: Internet :: WWW/HTTP
Classifier: Topic :: Security
Classifier: Topic :: System :: Networking
Classifier: Topic :: Internet :: Proxy Servers
